Metadata-Version: 1.1
Name: ssdedupe
Version: 0.0.3
Summary: A simple interface to datamade/dedupe to make probabilistic record linkage easy.
Home-page: https://github.com/melvin15may/ssdedupe
Author: Melvin Mathew
Author-email: melvin15may@gmail.com
License: MIT license
Keywords: ssdedupe
Platform: UNKNOWN
Classifier: Development Status :: 2 - Pre-Alpha
Classifier: Intended Audience :: Developers
Classifier: License :: OSI Approved :: MIT License
Classifier: Natural Language :: English
Classifier: Programming Language :: Python :: 2
Classifier: Programming Language :: Python :: 2.6
Classifier: Programming Language :: Python :: 2.7
Classifier: Programming Language :: Python :: 3
Classifier: Programming Language :: Python :: 3.3
Classifier: Programming Language :: Python :: 3.4
Classifier: Programming Language :: Python :: 3.5
